cvtools/__init__.py
cvtools/version.py
cvtools/data_augs/__init__.py
cvtools/data_augs/augmentations.py
cvtools/data_augs/check.py
cvtools/data_augs/datasets.py
cvtools/data_augs/generateor_thread.py
cvtools/data_augs/generator.py
cvtools/label_analysis/__init__.py
cvtools/label_analysis/coco_analysis.py
cvtools/label_analysis/crop_in_order.py
cvtools/label_analysis/dets_analysis.py
cvtools/label_convert/__init__.py
cvtools/label_convert/arcsoft_to_coco.py
cvtools/label_convert/bdd_to_coco.py
cvtools/label_convert/coco_to_jiang.py
cvtools/label_convert/coordinate_convert.py
cvtools/label_convert/jiang_label.py
cvtools/label_convert/jiang_to_coco.py
cvtools/label_convert/label_convert.py
cvtools/label_convert/rscup_to_coco.py
cvtools/label_convert/split_dataset.py
cvtools/label_convert/voc_label.py
cvtools/label_convert/arcsoft/__init__.py
cvtools/label_convert/arcsoft/attribute_combination.py
cvtools/pycocotools/__init__.py
cvtools/pycocotools/coco.py
cvtools/pycocotools/cocoeval.py
cvtools/utils/__init__.py
cvtools/utils/boxes.py
cvtools/utils/cluster.py
cvtools/utils/file.py
cvtools/utils/image.py
cvtools/utils/iou.py
cvtools/utils/label.py
cvtools/utils/timer.py
cvtoolss-0.0.2.dist-info/LICENSE
cvtoolss-0.0.2.dist-info/METADATA
cvtoolss-0.0.2.dist-info/WHEEL
cvtoolss-0.0.2.dist-info/top_level.txt
cvtoolss-0.0.2.dist-info/RECORD
